optional/__init__.py
optional/exceptions.py
optional/optional.py
optional/optional_property.py
optional/py.typed
py_optional-1.3.3.dist-info/AUTHORS.md
py_optional-1.3.3.dist-info/LICENSE
py_optional-1.3.3.dist-info/METADATA
py_optional-1.3.3.dist-info/WHEEL
py_optional-1.3.3.dist-info/RECORD
