Metadata-Version: 2.1
Name: py-optional
Version: 1.3.3
Summary: Optional value pattern for python
License: MIT
Author: Francisco Del Roio
Author-email: francipvb@hotmail.com
Requires-Python: >=3.8.1,<4.0.0
Classifier: License :: OSI Approved :: MIT License
Classifier: Programming Language :: Python :: 3
Classifier: Programming Language :: Python :: 3.9
Classifier: Programming Language :: Python :: 3.10
Classifier: Programming Language :: Python :: 3.11
Classifier: Programming Language :: Python :: 3.12
Requires-Dist: typing-extensions (>=4.5.0,<5.0.0)
